{
  "Indian National Congress": {"x": 0, "y": 0, "cost": 25, "days": 30, "prerequisites": [], "condition": "True", "effects": ["self.politicalPower += 75", "self.baseStability += 5"], "description": "+75 political power. +5 base stability. Unite the nationalist movement under the Congress.", "requirement_desc": "No additional requirements.", "exclusive_group": null},
  "Quit India": {"x": 0, "y": 1, "cost": 35, "days": 40, "prerequisites": ["Indian National Congress"], "condition": "True", "effects": ["self.politicalMultiplier += 0.15", "self.baseStability -= 5"], "description": "+15% political power gain. -5 base stability. Demand immediate independence.", "requirement_desc": "No additional requirements.", "exclusive_group": null},
  "Industrial India": {"x": 0, "y": 2, "cost": 40, "days": 50, "prerequisites": ["Quit India"], "condition": "True", "effects": ["self.addFactory()", "self.addFactory()", "self.moneyMultiplier += 0.1"], "description": "Build 2 factories. +10% money production. Develop heavy industry for self-reliance.", "requirement_desc": "No additional requirements.", "exclusive_group": null},
  "Five-Year Plan": {"x": 0, "y": 3, "cost": 50, "days": 60, "prerequisites": ["Industrial India"], "condition": "True", "effects": ["self.addFactory()", "self.money += 20000000", "self.buildSpeed -= 0.1"], "description": "Build 1 factory. Gain $20M. +10% build speed. State-led development planning.", "requirement_desc": "No additional requirements.", "exclusive_group": null},
  "Swadeshi Movement": {"x": 0, "y": 4, "cost": 30, "days": 35, "prerequisites": ["Indian National Congress"], "condition": "True", "effects": ["self.moneyMultiplier += 0.05", "self.baseStability += 5"], "description": "+5% money production. +5 base stability. Boycott foreign goods, promote Indian industry.", "requirement_desc": "No additional requirements.", "exclusive_group": null},
  "Constitutional Reform": {"x": 0, "y": 5, "cost": 45, "days": 55, "prerequisites": ["Five-Year Plan"], "condition": "True", "effects": ["self.baseStability += 15", "self.politicalMultiplier += 0.1"], "description": "+15 base stability. +10% political power gain. Draft a republican constitution.", "requirement_desc": "No additional requirements.", "exclusive_group": null},
  "British Indian Army": {"x": 200, "y": 0, "cost": 25, "days": 30, "prerequisites": [], "condition": "True", "effects": ["self.training.append([1, 0])", "self.defenseMultiplier += 0.05"], "description": "Train 1 division. +5% defense. Expand the colonial army.", "requirement_desc": "No additional requirements.", "exclusive_group": null},
  "Indianisation": {"x": 200, "y": 1, "cost": 30, "days": 40, "prerequisites": ["British Indian Army"], "condition": "True", "effects": ["self.attackMultiplier += 0.1", "self.training.append([1, 0])"], "description": "+10% attack. Train 1 division. Commission Indian officers.", "requirement_desc": "No additional requirements.", "exclusive_group": null},
  "Defence of India": {"x": 200, "y": 2, "cost": 35, "days": 45, "prerequisites": ["Indianisation"], "condition": "True", "effects": ["self.defenseMultiplier += 0.15", "self.addFactory()"], "description": "+15% defense. Build 1 factory. Prepare to defend the subcontinent.", "requirement_desc": "No additional requirements.", "exclusive_group": null},
  "Indian Navy": {"x": 200, "y": 3, "cost": 40, "days": 50, "prerequisites": ["Defence of India"], "condition": "True", "effects": ["self.transportMultiplier += 0.1", "self.defenseMultiplier += 0.05"], "description": "+10% transport speed. +5% defense. Build a blue-water navy.", "requirement_desc": "No additional requirements.", "exclusive_group": null},
  "Army Expansion": {"x": 200, "y": 4, "cost": 45, "days": 55, "prerequisites": ["Indian Navy"], "condition": "True", "effects": ["self.training.append([2, 0])", "self.attackMultiplier += 0.1"], "description": "Train 2 divisions. +10% attack. Expand the army for continental defence.", "requirement_desc": "No additional requirements.", "exclusive_group": null},
  "Eastern Command": {"x": 200, "y": 5, "cost": 40, "days": 50, "prerequisites": ["Army Expansion"], "condition": "True", "effects": ["self.defenseMultiplier += 0.1", "self.addFactory()"], "description": "+10% defense. Build 1 factory. Fortify the eastern frontier.", "requirement_desc": "No additional requirements.", "exclusive_group": null},
  "Green Revolution": {"x": 400, "y": 0, "cost": 30, "days": 45, "prerequisites": [], "condition": "True", "effects": ["self.moneyMultiplier += 0.15", "self.baseStability += 10"], "description": "+15% money production. +10 base stability. Modernise agriculture to feed the nation.", "requirement_desc": "No additional requirements.", "exclusive_group": null},
  "Dam Projects": {"x": 400, "y": 1, "cost": 40, "days": 55, "prerequisites": ["Green Revolution"], "condition": "True", "effects": ["self.money += 15000000", "self.addFactory()"], "description": "Gain $15M. Build 1 factory. Build great dams for irrigation and power.", "requirement_desc": "No additional requirements.", "exclusive_group": null},
  "Steel Plants": {"x": 400, "y": 2, "cost": 45, "days": 60, "prerequisites": ["Dam Projects"], "condition": "True", "effects": ["self.addFactory()", "self.addFactory()", "self.moneyMultiplier += 0.05"], "description": "Build 2 factories. +5% money production. Establish integrated steel plants.", "requirement_desc": "No additional requirements.", "exclusive_group": null},
  "Heavy Industry": {"x": 400, "y": 3, "cost": 55, "days": 70, "prerequisites": ["Steel Plants"], "condition": "True", "effects": ["self.addFactory()", "self.buildSpeed -= 0.1", "self.money += 10000000"], "description": "Build 1 factory. +10% build speed. Gain $10M. Machine tools and capital goods.", "requirement_desc": "No additional requirements.", "exclusive_group": null},
  "Textile Boom": {"x": 400, "y": 4, "cost": 35, "days": 45, "prerequisites": ["Green Revolution"], "condition": "True", "effects": ["self.money += 12000000", "self.moneyMultiplier += 0.05"], "description": "Gain $12M. +5% money production. Expand cotton and jute.", "requirement_desc": "No additional requirements.", "exclusive_group": null},
  "Railway Modernisation": {"x": 400, "y": 5, "cost": 50, "days": 60, "prerequisites": ["Heavy Industry"], "condition": "True", "effects": ["self.transportMultiplier += 0.2", "self.addFactory()"], "description": "+20% transport speed. Build 1 factory. Electrify and expand the rail network.", "requirement_desc": "No additional requirements.", "exclusive_group": null},
  "Non-Aligned Movement": {"x": 600, "y": 0, "cost": 35, "days": 40, "prerequisites": [], "condition": "True", "effects": ["self.baseStability += 10", "self.canMakeFaction = True"], "description": "+10 base stability. Unlocks faction creation. Lead the non-aligned nations.", "requirement_desc": "No additional requirements.", "exclusive_group": null},
  "Panchsheel": {"x": 600, "y": 1, "cost": 25, "days": 30, "prerequisites": ["Non-Aligned Movement"], "condition": "True", "effects": ["self.politicalPower += 50", "self.politicalMultiplier += 0.05"], "description": "+50 political power. +5% political power gain. Five principles of peaceful coexistence.", "requirement_desc": "No additional requirements.", "exclusive_group": null},
  "Nuclear Programme": {"x": 600, "y": 2, "cost": 75, "days": 90, "prerequisites": ["Steel Plants", "Panchsheel"], "condition": "True", "effects": ["self.attackMultiplier += 0.2", "self.money -= 20000000"], "description": "+20% attack. Lose $20M. Develop nuclear capability for deterrence.", "requirement_desc": "No additional requirements.", "exclusive_group": null},
  "Commonwealth Ties": {"x": 600, "y": 3, "cost": 30, "days": 35, "prerequisites": ["Non-Aligned Movement"], "condition": "True", "effects": ["self.money += 15000000", "self.politicalPower += 25"], "description": "Gain $15M. +25 political power. Maintain links with the Commonwealth.", "requirement_desc": "No additional requirements.", "exclusive_group": null},
  "Soviet Friendship": {"x": 600, "y": 4, "cost": 40, "days": 50, "prerequisites": ["Panchsheel"], "condition": "True", "effects": ["self.addFactory()", "self.money += 10000000"], "description": "Build 1 factory. Gain $10M. Accept Soviet technical and economic aid.", "requirement_desc": "No additional requirements.", "exclusive_group": null},
  "Regional Hegemon": {"x": 600, "y": 5, "cost": 60, "days": 75, "prerequisites": ["Nuclear Programme"], "condition": "True", "effects": ["self.attackMultiplier += 0.1", "self.expandedInvitations = True"], "description": "+10% attack. Unlocks expanded invitations. Dominant power in South Asia.", "requirement_desc": "No additional requirements.", "exclusive_group": null},
  "Conscription": {"x": 800, "y": 0, "cost": 40, "days": 45, "prerequisites": ["Indian Navy"], "condition": "not self.militarySize == 4", "effects": ["self.militarySize += 1", "self.training.append([2, 0])"], "description": "+1 military size. Train 2 divisions. Mobilise the population.", "requirement_desc": "Less than maximum military size.", "exclusive_group": null},
  "Rajputana Pride": {"x": 800, "y": 1, "cost": 30, "days": 35, "prerequisites": [], "condition": "True", "effects": ["self.attackMultiplier += 0.1", "self.baseStability += 5"], "description": "+10% attack. +5 base stability. Honour the martial traditions of Rajasthan.", "requirement_desc": "No additional requirements.", "exclusive_group": null},
  "Sikh Regiments": {"x": 800, "y": 2, "cost": 35, "days": 40, "prerequisites": ["Rajputana Pride"], "condition": "True", "effects": ["self.training.append([1, 0])", "self.defenseMultiplier += 0.1"], "description": "Train 1 division. +10% defense. Expand the Sikh light infantry.", "requirement_desc": "No additional requirements.", "exclusive_group": null},
  "Gurkha Brigades": {"x": 800, "y": 3, "cost": 40, "days": 50, "prerequisites": ["Sikh Regiments"], "condition": "True", "effects": ["self.training.append([1, 0])", "self.attackMultiplier += 0.15"], "description": "Train 1 division. +15% attack. Recruit and expand Gurkha units.", "requirement_desc": "No additional requirements.", "exclusive_group": null},
  "Mountain Corps": {"x": 800, "y": 4, "cost": 45, "days": 55, "prerequisites": ["Gurkha Brigades"], "condition": "True", "effects": ["self.defenseMultiplier += 0.15", "self.attackMultiplier += 0.1"], "description": "+15% defense. +10% attack. Specialise in Himalayan warfare.", "requirement_desc": "No additional requirements.", "exclusive_group": null},
  "National Mobilisation": {"x": 800, "y": 5, "cost": 55, "days": 65, "prerequisites": ["Conscription", "Mountain Corps"], "condition": "not self.militarySize == 4", "effects": ["self.militarySize += 1", "self.training.append([2, 0])", "self.defenseMultiplier += 0.1"], "description": "+1 military size. Train 2 divisions. +10% defense. Total war footing.", "requirement_desc": "Less than maximum military size.", "exclusive_group": null},
  "Bombay Port": {"x": 1000, "y": 0, "cost": 35, "days": 45, "prerequisites": [], "condition": "True", "effects": ["self.transportMultiplier += 0.1", "self.money += 10000000"], "description": "+10% transport speed. Gain $10M. Expand the gateway to India.", "requirement_desc": "No additional requirements.", "exclusive_group": null},
  "Calcutta Industry": {"x": 1000, "y": 1, "cost": 40, "days": 50, "prerequisites": ["Bombay Port"], "condition": "True", "effects": ["self.addFactory()", "self.moneyMultiplier += 0.05"], "description": "Build 1 factory. +5% money production. Develop Bengal industry.", "requirement_desc": "No additional requirements.", "exclusive_group": null},
  "Madras Development": {"x": 1000, "y": 2, "cost": 38, "days": 48, "prerequisites": ["Bombay Port"], "condition": "True", "effects": ["self.money += 8000000", "self.baseStability += 5"], "description": "Gain $8M. +5 base stability. Develop the southern presidency.", "requirement_desc": "No additional requirements.", "exclusive_group": null},
  "Punjab Breadbasket": {"x": 1000, "y": 3, "cost": 35, "days": 45, "prerequisites": ["Green Revolution"], "condition": "True", "effects": ["self.moneyMultiplier += 0.1", "self.money += 5000000"], "description": "+10% money production. Gain $5M. Maximise wheat and canal irrigation.", "requirement_desc": "No additional requirements.", "exclusive_group": null},
  "Assam Tea and Oil": {"x": 1000, "y": 4, "cost": 42, "days": 52, "prerequisites": ["Calcutta Industry"], "condition": "True", "effects": ["self.money += 6000000", "self.addFactory()"], "description": "Gain $6M. Build 1 factory. Develop Assam's resources.", "requirement_desc": "No additional requirements.", "exclusive_group": null},
  "United Subcontinent": {"x": 1000, "y": 5, "cost": 65, "days": 80, "prerequisites": ["Assam Tea and Oil", "Railway Modernisation"], "condition": "True", "effects": ["self.baseStability += 15", "self.transportMultiplier += 0.1"], "description": "+15 base stability. +10% transport speed. Integrate all regions.", "requirement_desc": "No additional requirements.", "exclusive_group": null},
  "Hindi as National Language": {"x": 1200, "y": 0, "cost": 25, "days": 30, "prerequisites": [], "condition": "True", "effects": ["self.baseStability += 5", "self.politicalPower += 50"], "description": "+5 base stability. +50 political power. Promote linguistic unity.", "requirement_desc": "No additional requirements.", "exclusive_group": null},
  "Scientific Temper": {"x": 1200, "y": 1, "cost": 40, "days": 50, "prerequisites": ["Hindi as National Language"], "condition": "True", "effects": ["self.buildSpeed -= 0.05", "self.politicalMultiplier += 0.05"], "description": "+5% build speed. +5% political power gain. Invest in science and education.", "requirement_desc": "No additional requirements.", "exclusive_group": null},
  "Space Programme": {"x": 1200, "y": 2, "cost": 70, "days": 85, "prerequisites": ["Nuclear Programme", "Scientific Temper"], "condition": "True", "effects": ["self.attackMultiplier += 0.1", "self.money -= 15000000"], "description": "+10% attack. Lose $15M. Establish ISRO and launch capability.", "requirement_desc": "No additional requirements.", "exclusive_group": null},
  "Caste Reform": {"x": 1200, "y": 3, "cost": 45, "days": 55, "prerequisites": ["Constitutional Reform"], "condition": "True", "effects": ["self.baseStability += 10", "self.ideology[1] += 0.1"], "description": "+10 base stability. Shift 10% libertarian. Erode caste barriers.", "requirement_desc": "No additional requirements.", "exclusive_group": null},
  "Secular Republic": {"x": 1200, "y": 4, "cost": 50, "days": 60, "prerequisites": ["Caste Reform"], "condition": "True", "effects": ["self.baseStability += 15", "self.politicalMultiplier += 0.1"], "description": "+15 base stability. +10% political power gain. Separate religion and state.", "requirement_desc": "No additional requirements.", "exclusive_group": null},
  "Indian Democracy": {"x": 1200, "y": 5, "cost": 60, "days": 70, "prerequisites": ["Secular Republic"], "condition": "True", "effects": ["self.baseStability += 20", "self.canMakeFaction = True"], "description": "+20 base stability. Unlocks faction creation. World's largest democracy.", "requirement_desc": "No additional requirements.", "exclusive_group": null},
  "Indian Air Force": {"x": 1400, "y": 0, "cost": 45, "days": 55, "prerequisites": ["Army Expansion"], "condition": "True", "effects": ["self.attackMultiplier += 0.15", "self.training.append([1, 0])"], "description": "+15% attack. Train 1 division. Build an independent air arm.", "requirement_desc": "No additional requirements.", "exclusive_group": null},
  "Carrier Ambition": {"x": 1400, "y": 1, "cost": 65, "days": 80, "prerequisites": ["Indian Navy", "Heavy Industry"], "condition": "True", "effects": ["self.transportMultiplier += 0.15", "self.defenseMultiplier += 0.1", "self.money -= 10000000"], "description": "+15% transport speed. +10% defense. Lose $10M. Project power at sea.", "requirement_desc": "No additional requirements.", "exclusive_group": null},
  "Desert Corps": {"x": 1400, "y": 2, "cost": 40, "days": 50, "prerequisites": ["Rajputana Pride"], "condition": "True", "effects": ["self.attackMultiplier += 0.1", "self.defenseMultiplier += 0.1"], "description": "+10% attack. +10% defense. Specialise in Rajasthan and Thar.", "requirement_desc": "No additional requirements.", "exclusive_group": null},
  "Armoured Division": {"x": 1400, "y": 3, "cost": 55, "days": 65, "prerequisites": ["Desert Corps", "Steel Plants"], "condition": "True", "effects": ["self.training.append([1, 0])", "self.attackMultiplier += 0.2"], "description": "Train 1 division. +20% attack. Form armoured strike force.", "requirement_desc": "No additional requirements.", "exclusive_group": null},
  "Defence Research": {"x": 1400, "y": 4, "cost": 50, "days": 60, "prerequisites": ["Nuclear Programme"], "condition": "True", "effects": ["self.defenseMultiplier += 0.1", "self.buildSpeed -= 0.05"], "description": "+10% defense. +5% build speed. DRDO and indigenous weapons.", "requirement_desc": "No additional requirements.", "exclusive_group": null},
  "Great Power India": {"x": 1400, "y": 5, "cost": 75, "days": 90, "prerequisites": ["Regional Hegemon", "Indian Democracy", "Carrier Ambition"], "condition": "True", "effects": ["self.attackMultiplier += 0.15", "self.defenseMultiplier += 0.15", "self.baseStability += 10"], "description": "+15% attack. +15% defense. +10 base stability. Claim a seat at the top table.", "requirement_desc": "No additional requirements.", "exclusive_group": null},
  "Bollywood and Culture": {"x": 1200, "y": 6, "cost": 30, "days": 40, "prerequisites": ["Hindi as National Language"], "condition": "True", "effects": ["self.baseStability += 10", "self.money += 5000000"], "description": "+10 base stability. Gain $5M. Promote film and cultural influence.", "requirement_desc": "No additional requirements.", "exclusive_group": null},
  "Coastal Defence": {"x": 200, "y": 6, "cost": 38, "days": 48, "prerequisites": ["Eastern Command"], "condition": "True", "effects": ["self.defenseMultiplier += 0.1", "self.transportMultiplier += 0.05"], "description": "+10% defense. +5% transport speed. Secure the coastline.", "requirement_desc": "No additional requirements.", "exclusive_group": null}
}
